pyvoikko/__init__.py
pyvoikko/analysis.py
pyvoikko/constants.py
pyvoikko/voikko.kfst
pyvoikko-0.6.dist-info/LICENSE
pyvoikko-0.6.dist-info/METADATA
pyvoikko-0.6.dist-info/WHEEL
pyvoikko-0.6.dist-info/top_level.txt
pyvoikko-0.6.dist-info/RECORD
